atmoswing_api/__init__.py
atmoswing_api/__version__.py
atmoswing_api/cache.py
atmoswing_api/config.py
atmoswing_api/app/__init__.py
atmoswing_api/app/main.py
atmoswing_api/app/models/__init__.py
atmoswing_api/app/models/models.py
atmoswing_api/app/routes/__init__.py
atmoswing_api/app/routes/aggregations.py
atmoswing_api/app/routes/docs.py
atmoswing_api/app/routes/forecasts.py
atmoswing_api/app/routes/meta.py
atmoswing_api/app/services/__init__.py
atmoswing_api/app/services/aggregations.py
atmoswing_api/app/services/forecasts.py
atmoswing_api/app/services/meta.py
atmoswing_api/app/utils/__init__.py
atmoswing_api/app/utils/logger.py
atmoswing_api/app/utils/utils.py
atmoswing_api/scripts/cleaner.py
atmoswing_api/scripts/export_docs.py
atmoswing_api/scripts/warmup_cache.py
atmoswing_api-1.1.0.dist-info/licenses/LICENSE
atmoswing_api-1.1.0.dist-info/METADATA
atmoswing_api-1.1.0.dist-info/WHEEL
atmoswing_api-1.1.0.dist-info/top_level.txt
atmoswing_api-1.1.0.dist-info/RECORD
