Metadata-Version: 2.4
Name: atmoswing-api
Version: 1.1.0
Summary: A web API for AtmoSwing forecasts
Author-email: Pascal Horton <pascal.horton@terranum.ch>
License: MIT License
Classifier: Programming Language :: Python :: 3
Classifier: License :: OSI Approved :: MIT License
Classifier: Operating System :: OS Independent
Requires-Python: >=3.10
License-File: LICENSE
Requires-Dist: fastapi
Requires-Dist: uvicorn[standard]
Requires-Dist: xarray
Requires-Dist: h5netcdf
Requires-Dist: pydantic
Requires-Dist: pydantic-settings
Requires-Dist: python-dotenv
Requires-Dist: dask
Requires-Dist: pytest
Requires-Dist: pytest-asyncio
Dynamic: license-file
